README.md
setup.py
short_url_expander.egg-info/PKG-INFO
short_url_expander.egg-info/SOURCES.txt
short_url_expander.egg-info/dependency_links.txt
short_url_expander.egg-info/requires.txt
short_url_expander.egg-info/top_level.txt
url_expander/__init__.py
url_expander/api_client.py
url_expander/configuration.py
url_expander/rest.py
url_expander/api/__init__.py
url_expander/api/url_expander_api.py
url_expander/models/__init__.py
url_expander/models/inline_response200.py
url_expander/models/inline_response200_data.py
url_expander/models/inline_response400.py
url_expander/models/inline_response500.py
url_expander/models/one_ofinline_response200_data_error_msg.py
url_expander/models/one_ofinline_response200_data_redirect_url.py
url_expander/models/tools_urlexpander_body.py