Metadata-Version: 2.1
Name: short-url-expander
Version: 1.0.0
Summary: LinksGPT URL Expander SDK, provides an easy way to interact with the URL Expander API - Expand shortened URLs (short link) and retrieves details about redirections and the final destination URL.
Home-page: https://github.com/LinksGPT/url-expander-sdk-python
Author: LinksGPT
Author-email: service@linksgpt.com
License: MIT License
Keywords: SEO,url,expand,link,social media
Platform: UNKNOWN
